dockerly/__init__.py
dockerly-0.0.0.dist-info/METADATA
dockerly-0.0.0.dist-info/RECORD
dockerly-0.0.0.dist-info/WHEEL
dockerly-0.0.0.dist-info/top_level.txt
