Metadata-Version: 2.1
Name: dockerly
Version: 0.0.0
Summary: dockerly library.
Home-page: UNKNOWN
Author: Dr. F
Author-email: UNKNOWN
License: GPLv3
Platform: UNKNOWN
Classifier: Development Status :: 4 - Beta
Classifier: Programming Language :: Python :: 3
